MANIFEST.in
README.md
setup.py
dash_colorscales/__init__.py
dash_colorscales/bundle.js
dash_colorscales/metadata.json
dash_colorscales/version.py
dash_colorscales.egg-info/PKG-INFO
dash_colorscales.egg-info/SOURCES.txt
dash_colorscales.egg-info/dependency_links.txt
dash_colorscales.egg-info/top_level.txt