Metadata-Version: 1.0
Name: dash-colorscales
Version: 0.0.3
Summary: Colorscale picker UI for your Dash apps
Home-page: UNKNOWN
Author: plotly
Author-email: UNKNOWN
License: MIT
Platform: UNKNOWN
